LICENCE.txt
MANIFEST.in
README.md
setup.py
XDC3PYTHON/__init__.py
XDC3PYTHON/createAccount.py
XDC3PYTHON/xrc20.py
XDC3PYTHON/xrc721.py
XDC3PYTHON.egg-info/PKG-INFO
XDC3PYTHON.egg-info/SOURCES.txt
XDC3PYTHON.egg-info/dependency_links.txt
XDC3PYTHON.egg-info/top_level.txt