Metadata-Version: 2.1
Name: XDC3PYTHON
Version: 1.0.1
Summary: XDC RUST SDK with support for smart contracts, XRC20 & XRC721
Home-page: https://github.com/XDCFoundation/XDC_Python_SDK_V1.git
Author: XDC Foundation
License: MIT
Platform: UNKNOWN
License-File: LICENCE.txt
